{
  "$schema": "../../iscwsa_schema/draft.json",
  "metadata": {
    "schema_uuid": "00000000-0000-0000-0000-000000000000",
    "model_uuid": "32457c7e-bb34-5019-b2ae-490af5dfdcc0",
    "model_id": "B007Mc",
    "short_name": "MWD+LRGM+AX_Fl",
    "long_name": "OWSG MWD + LRGM + Axial Correction [Floating Rig]",
    "revision_number": 5,
    "revision_date": "2020-10-08",
    "revision_comment": "Rev No changed to match ISCWSA Models (Rev.5). XCLA & XCLH terms added. XYM3 replaced by XYM3E. XYM4 replaced by XYM4E. SAG replaced by SAGE. DECG replaced by DEC-U DEC-OS DEC-OH DEC-OI. DBHG replaced by DBH-U DBH-OS DBH-OH DBH-OI.MFIG replaced by MFI-U MFI-OS MFI-OH MFI-OI. MDIG replaced by MDI-U MDI-OS MDI-OH MDI-OI. Updated Short Name, Long Name, Application.",
    "source": "OWSG - SPE 67616 and 63275",
    "application": "MWD using Low Resolution Geomagnetic Model (e.g. Updated less frequently than yearly, EMM, CGRF, IGRF, WMM) with Axial Correction on a Floating Rig",
    "tool_type": "Magnetic",
    "author": "welleng OWSG-to-ISCWSA converter",
    "framework": "ISCWSA Rev5",
    "tags": [
      "owsg-setb",
      "sheet-MWD+LRGM+AX_Fl",
      "source-xlsx:toolgroup-owsg-b-rev-5-1-08-oct-2020-produced-23-sep-2022.xlsx",
      "warn:term 'DSFS': unit '-' not in ISCWSA enum ['1/m', 'deg', 'deg/hr', 'deg/nT', 'm', 'm/s2', 'nT', 'rad']",
      "warn:term 'ASIXY-TI1S': unit '-' not in ISCWSA enum ['1/m', 'deg', 'deg/hr', 'deg/nT', 'm', 'm/s2', 'nT', 'rad']",
      "warn:term 'ASIXY-TI2S': unit '-' not in ISCWSA enum ['1/m', 'deg', 'deg/hr', 'deg/nT', 'm', 'm/s2', 'nT', 'rad']",
      "warn:term 'ASIXY-TI3S': unit '-' not in ISCWSA enum ['1/m', 'deg', 'deg/hr', 'deg/nT', 'm', 'm/s2', 'nT', 'rad']",
      "warn:term 'ASIZ': unit '-' not in ISCWSA enum ['1/m', 'deg', 'deg/hr', 'deg/nT', 'm', 'm/s2', 'nT', 'rad']"
    ]
  },
  "parameters": {
    "inc_min": 0,
    "inc_max": 180
  },
  "terms": [
    {
      "uuid": "fd2e3aeb-f038-5405-87dc-772a6ea817e2",
      "name": "DRFR",
      "x_owsg_weight_function": "DREF",
      "value": 2.2,
      "units": "m",
      "depth_factor": 0,
      "inclination_factor": 0,
      "azimuth_factor": 0,
      "propagation_mode": "Random",
      "depth_formula": "1",
      "inclination_formula": "0",
      "azimuth_formula": "0",
      "north_singularity": null,
      "east_singularity": null,
      "vertical_singularity": null,
      "hash_value": "00000000000000000000000000000000"
    },
    {
      "uuid": "b9a1b65c-9fbd-5d2a-b7a9-a6bfef5fffa3",
      "name": "DRFS",
      "x_owsg_weight_function": "DREF",
      "value": 1.0,
      "units": "m",
      "depth_factor": 1,
      "inclination_factor": 0,
      "azimuth_factor": 0,
      "propagation_mode": "Systematic",
      "depth_formula": "1",
      "inclination_formula": "0",
      "azimuth_formula": "0",
      "north_singularity": null,
      "east_singularity": null,
      "vertical_singularity": null,
      "hash_value": "00000000000000000000000000000000"
    },
    {
      "uuid": "280092de-c625-5595-bb6c-fc312435c713",
      "name": "DSFS",
      "x_owsg_weight_function": "DSF",
      "value": 0.00056,
      "units": "-",
      "depth_factor": 1,
      "inclination_factor": 0,
      "azimuth_factor": 0,
      "propagation_mode": "Systematic",
      "depth_formula": "MD",
      "inclination_formula": "0",
      "azimuth_formula": "0",
      "north_singularity": null,
      "east_singularity": null,
      "vertical_singularity": null,
      "hash_value": "00000000000000000000000000000000"
    },
    {
      "uuid": "e98a3551-8d28-56bf-9f4e-80bfc4cac372",
      "name": "DSTG",
      "x_owsg_weight_function": "DST",
      "value": 2.5e-07,
      "units": "1/m",
      "depth_factor": 1,
      "inclination_factor": 1,
      "azimuth_factor": 1,
      "propagation_mode": "Global",
      "depth_formula": "MD * TVD",
      "inclination_formula": "0",
      "azimuth_formula": "0",
      "north_singularity": null,
      "east_singularity": null,
      "vertical_singularity": null,
      "hash_value": "00000000000000000000000000000000"
    },
    {
      "uuid": "be058995-d848-5895-b389-500f1acbcb3c",
      "name": "ABIXY-TI1S",
      "x_owsg_weight_function": "ABIXY-TI1",
      "value": 0.004,
      "units": "m/s2",
      "depth_factor": 1,
      "inclination_factor": 0,
      "azimuth_factor": 0,
      "propagation_mode": "Systematic",
      "depth_formula": "0",
      "inclination_formula": "-Cos(Inc) / Gfield",
      "azimuth_formula": "(Cos(Inc) * Cos(Inc) * Sin(AzM) * (Tan(Dip) * Cos(Inc) + Sin(Inc) * Cos(AzM))) / (GField * (1 - Sin(Inc) * Sin(Inc) * Sin(AzM) * Sin(AzM)))",
      "north_singularity": null,
      "east_singularity": null,
      "vertical_singularity": null,
      "hash_value": "00000000000000000000000000000000"
    },
    {
      "uuid": "d6ed3b58-16a5-5e4e-a2c8-72c6cf7e5813",
      "name": "ABIXY-TI2S",
      "x_owsg_weight_function": "ABIXY-TI2",
      "value": 0.004,
      "units": "m/s2",
      "depth_factor": 1,
      "inclination_factor": 0,
      "azimuth_factor": 0,
      "propagation_mode": "Systematic",
      "depth_formula": "0",
      "inclination_formula": "0",
      "azimuth_formula": "-(Tan(Dip) * Cos(AzM) - Tan(90 * RAD - Inc)) / (GField * (1 - Sin(Inc) * Sin(Inc) * Sin(AzM) * Sin(AzM)))",
      "north_singularity": "-Sin(Az) / Gfield",
      "east_singularity": "Cos(Az) / Gfield",
      "vertical_singularity": null,
      "hash_value": "00000000000000000000000000000000"
    },
    {
      "uuid": "92d1f687-7ffe-527c-9e51-0dde866ad1d0",
      "name": "ABIZ",
      "x_owsg_weight_function": "ABIZ",
      "value": 0.004,
      "units": "m/s2",
      "depth_factor": 1,
      "inclination_factor": 0,
      "azimuth_factor": 0,
      "propagation_mode": "Systematic",
      "depth_formula": "0",
      "inclination_formula": "-Sin(Inc) / Gfield",
      "azimuth_formula": "(Sin(Inc) * Cos(Inc) * Sin(AzM) * (Tan(Dip) * Cos(Inc) + Sin(Inc) * Cos(AzM))) / (1 - Sin(Inc) * Sin(Inc) * Sin(AzM) * Sin(AzM)) / Gfield",
      "north_singularity": null,
      "east_singularity": null,
      "vertical_singularity": null,
      "hash_value": "00000000000000000000000000000000"
    },
    {
      "uuid": "db0c6983-602d-59ec-b067-443fdd787c8b",
      "name": "ASIXY-TI1S",
      "x_owsg_weight_function": "ASIXY-TI1",
      "value": 0.0005,
      "units": "-",
      "depth_factor": 1,
      "inclination_factor": 0,
      "azimuth_factor": 0,
      "propagation_mode": "Systematic",
      "depth_formula": "0",
      "inclination_formula": "Sin(Inc) * Cos(Inc) / Sqr(2)",
      "azimuth_formula": "-(Sin(Inc) * Cos(Inc) * Cos(Inc) * Sin(AzM) * (Tan(Dip) * Cos(Inc) + Sin(Inc) * Cos(AzM))) / (Sqr(2) * (1 - Sin(Inc) * Sin(Inc) * Sin(AzM) * Sin(AzM)))",
      "north_singularity": null,
      "east_singularity": null,
      "vertical_singularity": null,
      "hash_value": "00000000000000000000000000000000"
    },
    {
      "uuid": "6be05209-f19a-5ca5-9525-1fbac4fa65e5",
      "name": "ASIXY-TI2S",
      "x_owsg_weight_function": "ASIXY-TI2",
      "value": 0.0005,
      "units": "-",
      "depth_factor": 1,
      "inclination_factor": 0,
      "azimuth_factor": 0,
      "propagation_mode": "Systematic",
      "depth_formula": "0",
      "inclination_formula": "Sin(Inc) * Cos(Inc) / 2",
      "azimuth_formula": "-(Sin(Inc) * Cos(Inc) * Cos(Inc) * Sin(AzM) * (Tan(Dip) * Cos(Inc) + Sin(Inc) * Cos(AzM))) / (2 * (1 - Sin(Inc) * Sin(Inc) * Sin(AzM) * Sin(AzM)))",
      "north_singularity": null,
      "east_singularity": null,
      "vertical_singularity": null,
      "hash_value": "00000000000000000000000000000000"
    },
    {
      "uuid": "7ca9e2fa-cbf5-5eef-b92c-3ae3b0371dc7",
      "name": "ASIXY-TI3S",
      "x_owsg_weight_function": "ASIXY-TI3",
      "value": 0.0005,
      "units": "-",
      "depth_factor": 1,
      "inclination_factor": 0,
      "azimuth_factor": 0,
      "propagation_mode": "Systematic",
      "depth_formula": "0",
      "inclination_formula": "0",
      "azimuth_formula": "(Tan(Dip) * Sin(Inc) * Cos(AzM) - Cos(Inc)) / (2 * (1 - Sin(Inc) * Sin(Inc) * Sin(AzM) * Sin(AzM)))",
      "north_singularity": null,
      "east_singularity": null,
      "vertical_singularity": null,
      "hash_value": "00000000000000000000000000000000"
    },
    {
      "uuid": "e6c57ce4-5f38-5b48-beed-f273cb82eb7c",
      "name": "ASIZ",
      "x_owsg_weight_function": "ASIZ",
      "value": 0.0005,
      "units": "-",
      "depth_factor": 1,
      "inclination_factor": 0,
      "azimuth_factor": 0,
      "propagation_mode": "Systematic",
      "depth_formula": "0",
      "inclination_formula": "-Sin(Inc) * Cos(Inc)",
      "azimuth_formula": "Sin(Inc) * Cos(Inc) * Cos(Inc) * Sin(AzM) * (Tan(Dip) * Cos(Inc) + Sin(Inc) * Cos(AzM)) / (1 - Sin(Inc) * Sin(Inc) * Sin(AzM) * Sin(AzM))",
      "north_singularity": null,
      "east_singularity": null,
      "vertical_singularity": null,
      "hash_value": "00000000000000000000000000000000"
    },
    {
      "uuid": "ac5df650-7ada-545f-9385-5b08f6e278e3",
      "name": "MBIXY-TI1S",
      "x_owsg_weight_function": "MBIXY-TI1",
      "value": 70.0,
      "units": "nT",
      "depth_factor": 1,
      "inclination_factor": 0,
      "azimuth_factor": 0,
      "propagation_mode": "Systematic",
      "depth_formula": "0",
      "inclination_formula": "0",
      "azimuth_formula": "-Cos(Inc) * Sin(AzM) / (BField * Cos(Dip) * (1 - Sin(Inc) * Sin(Inc) * Sin(AzM) * Sin(AzM)))",
      "north_singularity": null,
      "east_singularity": null,
      "vertical_singularity": null,
      "hash_value": "00000000000000000000000000000000"
    },
    {
      "uuid": "4b574469-6737-5b1a-8266-47436e7b6fa3",
      "name": "MBIXY-TI2S",
      "x_owsg_weight_function": "MBIXY-TI2",
      "value": 70.0,
      "units": "nT",
      "depth_factor": 1,
      "inclination_factor": 0,
      "azimuth_factor": 0,
      "propagation_mode": "Systematic",
      "depth_formula": "0",
      "inclination_formula": "0",
      "azimuth_formula": "Cos(AzM) / (BField * Cos(Dip) * (1 - Sin(Inc) * Sin(Inc) * Sin(AzM) * Sin(AzM)))",
      "north_singularity": null,
      "east_singularity": null,
      "vertical_singularity": null,
      "hash_value": "00000000000000000000000000000000"
    },
    {
      "uuid": "608e5f26-066e-5fce-a6db-725c94b9cbd3",
      "name": "MSIXY-TI1S",
      "x_owsg_weight_function": "MSIXY-TI1",
      "value": 0.0016,
      "units": "-",
      "depth_factor": 1,
      "inclination_factor": 0,
      "azimuth_factor": 0,
      "propagation_mode": "Systematic",
      "depth_formula": "0",
      "inclination_formula": "0",
      "azimuth_formula": "Sin(Inc) * Sin(AzM) * (Tan(Dip) * Cos(Inc) + Sin(Inc) * Cos(AzM)) / (Sqr(2) * (1 - Sin(Inc) * Sin(Inc) * Sin(AzM) * Sin(AzM)))",
      "north_singularity": null,
      "east_singularity": null,
      "vertical_singularity": null,
      "hash_value": "00000000000000000000000000000000"
    },
    {
      "uuid": "ca76bd90-71a8-5951-bfae-9d2683df161c",
      "name": "MSIXY-TI2S",
      "x_owsg_weight_function": "MSIXY-TI2",
      "value": 0.0016,
      "units": "-",
      "depth_factor": 1,
      "inclination_factor": 0,
      "azimuth_factor": 0,
      "propagation_mode": "Systematic",
      "depth_formula": "0",
      "inclination_formula": "0",
      "azimuth_formula": "Sin(AzM) * (Tan(Dip) * Sin(Inc) * Cos(Inc) - Cos(Inc) * Cos(Inc) * Cos(AzM) - Cos(AzM)) / (2 * (1 - Sin(Inc) * Sin(Inc) * Sin(AzM) * Sin(AzM)))",
      "north_singularity": null,
      "east_singularity": null,
      "vertical_singularity": null,
      "hash_value": "00000000000000000000000000000000"
    },
    {
      "uuid": "1dcb211e-a804-59da-81af-0b7341785faf",
      "name": "MSIXY-TI3S",
      "x_owsg_weight_function": "MSIXY-TI3",
      "value": 0.0016,
      "units": "-",
      "depth_factor": 1,
      "inclination_factor": 0,
      "azimuth_factor": 0,
      "propagation_mode": "Systematic",
      "depth_formula": "0",
      "inclination_formula": "0",
      "azimuth_formula": "(Cos(Inc) * Cos(AzM) * Cos(AzM) - Cos(Inc) * Sin(AzM) * Sin(AzM) - Tan(Dip) * Sin(Inc) * Cos(AzM)) / (2 * (1 - Sin(Inc) * Sin(Inc) * Sin(AzM) * Sin(AzM)))",
      "north_singularity": null,
      "east_singularity": null,
      "vertical_singularity": null,
      "hash_value": "00000000000000000000000000000000"
    },
    {
      "uuid": "3c3adc3e-0354-5df5-97b4-77511b8713dd",
      "name": "DEC-U",
      "x_owsg_weight_function": "AZ",
      "value": 0.29,
      "units": "deg",
      "depth_factor": 1,
      "inclination_factor": 1,
      "azimuth_factor": 0,
      "propagation_mode": "Well",
      "depth_formula": "0",
      "inclination_formula": "0",
      "azimuth_formula": "1",
      "north_singularity": null,
      "east_singularity": null,
      "vertical_singularity": null,
      "hash_value": "00000000000000000000000000000000"
    },
    {
      "uuid": "9e1534c1-4108-5efa-9c8b-9a147aeda074",
      "name": "DEC-OS",
      "x_owsg_weight_function": "AZ",
      "value": 0.24,
      "units": "deg",
      "depth_factor": 1,
      "inclination_factor": 1,
      "azimuth_factor": 1,
      "propagation_mode": "Global",
      "depth_formula": "0",
      "inclination_formula": "0",
      "azimuth_formula": "1",
      "north_singularity": null,
      "east_singularity": null,
      "vertical_singularity": null,
      "hash_value": "00000000000000000000000000000000"
    },
    {
      "uuid": "49f0e3fd-aca2-521c-87ce-f5eceae6ce82",
      "name": "DEC-OH",
      "x_owsg_weight_function": "AZ",
      "value": 0.21,
      "units": "deg",
      "depth_factor": 1,
      "inclination_factor": 1,
      "azimuth_factor": 1,
      "propagation_mode": "Global",
      "depth_formula": "0",
      "inclination_formula": "0",
      "azimuth_formula": "1",
      "north_singularity": null,
      "east_singularity": null,
      "vertical_singularity": null,
      "hash_value": "00000000000000000000000000000000"
    },
    {
      "uuid": "6f3fa313-9529-53b8-a934-7748c2d015b0",
      "name": "DEC-OI",
      "x_owsg_weight_function": "AZ",
      "value": 0.05,
      "units": "deg",
      "depth_factor": 1,
      "inclination_factor": 1,
      "azimuth_factor": 1,
      "propagation_mode": "Global",
      "depth_formula": "0",
      "inclination_formula": "0",
      "azimuth_formula": "1",
      "north_singularity": null,
      "east_singularity": null,
      "vertical_singularity": null,
      "hash_value": "00000000000000000000000000000000"
    },
    {
      "uuid": "f600b3dc-731a-54a3-91c4-66513a69c921",
      "name": "DECR",
      "x_owsg_weight_function": "AZ",
      "value": 0.1,
      "units": "deg",
      "depth_factor": 0,
      "inclination_factor": 0,
      "azimuth_factor": 0,
      "propagation_mode": "Random",
      "depth_formula": "0",
      "inclination_formula": "0",
      "azimuth_formula": "1",
      "north_singularity": null,
      "east_singularity": null,
      "vertical_singularity": null,
      "hash_value": "00000000000000000000000000000000"
    },
    {
      "uuid": "bce57eb2-f51e-5e0e-8f6f-33755134fde8",
      "name": "DBH-U",
      "x_owsg_weight_function": "DBH",
      "value": 4108.0,
      "units": "deg.nT",
      "depth_factor": 1,
      "inclination_factor": 1,
      "azimuth_factor": 0,
      "propagation_mode": "Well",
      "depth_formula": "0",
      "inclination_formula": "0",
      "azimuth_formula": "1 / (BField * Cos(Dip))",
      "north_singularity": null,
      "east_singularity": null,
      "vertical_singularity": null,
      "hash_value": "00000000000000000000000000000000"
    },
    {
      "uuid": "68f37017-f071-57fb-b532-7b0fdfa00919",
      "name": "DBH-OS",
      "x_owsg_weight_function": "DBH",
      "value": 3359.0,
      "units": "deg.nT",
      "depth_factor": 1,
      "inclination_factor": 1,
      "azimuth_factor": 1,
      "propagation_mode": "Global",
      "depth_formula": "0",
      "inclination_formula": "0",
      "azimuth_formula": "1 / (BField * Cos(Dip))",
      "north_singularity": null,
      "east_singularity": null,
      "vertical_singularity": null,
      "hash_value": "00000000000000000000000000000000"
    },
    {
      "uuid": "21f79fdd-d495-5ad5-84a1-6091802395bf",
      "name": "DBH-OH",
      "x_owsg_weight_function": "DBH",
      "value": 2840.0,
      "units": "deg.nT",
      "depth_factor": 1,
      "inclination_factor": 1,
      "azimuth_factor": 1,
      "propagation_mode": "Global",
      "depth_formula": "0",
      "inclination_formula": "0",
      "azimuth_formula": "1 / (BField * Cos(Dip))",
      "north_singularity": null,
      "east_singularity": null,
      "vertical_singularity": null,
      "hash_value": "00000000000000000000000000000000"
    },
    {
      "uuid": "02575354-26a5-538b-9234-e1a5f51dc529",
      "name": "DBH-OI",
      "x_owsg_weight_function": "DBH",
      "value": 356.0,
      "units": "deg.nT",
      "depth_factor": 1,
      "inclination_factor": 1,
      "azimuth_factor": 1,
      "propagation_mode": "Global",
      "depth_formula": "0",
      "inclination_formula": "0",
      "azimuth_formula": "1 / (BField * Cos(Dip))",
      "north_singularity": null,
      "east_singularity": null,
      "vertical_singularity": null,
      "hash_value": "00000000000000000000000000000000"
    },
    {
      "uuid": "94b9946f-78c8-56a7-9f8a-5be602a6883d",
      "name": "DBHR",
      "x_owsg_weight_function": "DBH",
      "value": 3000.0,
      "units": "deg.nT",
      "depth_factor": 0,
      "inclination_factor": 0,
      "azimuth_factor": 0,
      "propagation_mode": "Random",
      "depth_formula": "0",
      "inclination_formula": "0",
      "azimuth_formula": "1 / (BField * Cos(Dip))",
      "north_singularity": null,
      "east_singularity": null,
      "vertical_singularity": null,
      "hash_value": "00000000000000000000000000000000"
    },
    {
      "uuid": "d09278ba-0fe2-56d2-ad61-081aa35fe3f5",
      "name": "MDI-U",
      "x_owsg_weight_function": "MDI",
      "value": 0.16,
      "units": "deg",
      "depth_factor": 1,
      "inclination_factor": 1,
      "azimuth_factor": 0,
      "propagation_mode": "Well",
      "depth_formula": "0",
      "inclination_formula": "0",
      "azimuth_formula": "-Sin(Inc) * Sin(AzM) * (Cos(Inc) - Tan(Dip) * Sin(Inc) * Cos(AzM)) / (1 - Sin(Inc) * Sin(Inc) * Sin(AzM) * Sin(AzM))",
      "north_singularity": null,
      "east_singularity": null,
      "vertical_singularity": null,
      "hash_value": "00000000000000000000000000000000"
    },
    {
      "uuid": "bb195b3e-536a-5f33-a768-1568193b5555",
      "name": "MDI-OS",
      "x_owsg_weight_function": "MDI",
      "value": 0.14,
      "units": "deg",
      "depth_factor": 1,
      "inclination_factor": 1,
      "azimuth_factor": 1,
      "propagation_mode": "Global",
      "depth_formula": "0",
      "inclination_formula": "0",
      "azimuth_formula": "-Sin(Inc) * Sin(AzM) * (Cos(Inc) - Tan(Dip) * Sin(Inc) * Cos(AzM)) / (1 - Sin(Inc) * Sin(Inc) * Sin(AzM) * Sin(AzM))",
      "north_singularity": null,
      "east_singularity": null,
      "vertical_singularity": null,
      "hash_value": "00000000000000000000000000000000"
    },
    {
      "uuid": "956a249d-77b0-50ca-bc86-6a30912c1e3e",
      "name": "MDI-OH",
      "x_owsg_weight_function": "MDI",
      "value": 0.11,
      "units": "deg",
      "depth_factor": 1,
      "inclination_factor": 1,
      "azimuth_factor": 1,
      "propagation_mode": "Global",
      "depth_formula": "0",
      "inclination_formula": "0",
      "azimuth_formula": "-Sin(Inc) * Sin(AzM) * (Cos(Inc) - Tan(Dip) * Sin(Inc) * Cos(AzM)) / (1 - Sin(Inc) * Sin(Inc) * Sin(AzM) * Sin(AzM))",
      "north_singularity": null,
      "east_singularity": null,
      "vertical_singularity": null,
      "hash_value": "00000000000000000000000000000000"
    },
    {
      "uuid": "22b15564-3178-54ed-8f36-26b7ed1bd94d",
      "name": "MDI-OI",
      "x_owsg_weight_function": "MDI",
      "value": 0.03,
      "units": "deg",
      "depth_factor": 1,
      "inclination_factor": 1,
      "azimuth_factor": 1,
      "propagation_mode": "Global",
      "depth_formula": "0",
      "inclination_formula": "0",
      "azimuth_formula": "-Sin(Inc) * Sin(AzM) * (Cos(Inc) - Tan(Dip) * Sin(Inc) * Cos(AzM)) / (1 - Sin(Inc) * Sin(Inc) * Sin(AzM) * Sin(AzM))",
      "north_singularity": null,
      "east_singularity": null,
      "vertical_singularity": null,
      "hash_value": "00000000000000000000000000000000"
    },
    {
      "uuid": "7dc23ecc-ed31-5a21-9557-8cfc0be4ae57",
      "name": "MDIR",
      "x_owsg_weight_function": "MDI",
      "value": 0.08,
      "units": "deg",
      "depth_factor": 0,
      "inclination_factor": 0,
      "azimuth_factor": 0,
      "propagation_mode": "Random",
      "depth_formula": "0",
      "inclination_formula": "0",
      "azimuth_formula": "-Sin(Inc) * Sin(AzM) * (Cos(Inc) - Tan(Dip) * Sin(Inc) * Cos(AzM)) / (1 - Sin(Inc) * Sin(Inc) * Sin(AzM) * Sin(AzM))",
      "north_singularity": null,
      "east_singularity": null,
      "vertical_singularity": null,
      "hash_value": "00000000000000000000000000000000"
    },
    {
      "uuid": "54394827-285f-5774-b7d3-bbcad8b2a4c1",
      "name": "MFI-U",
      "x_owsg_weight_function": "MFI",
      "value": 107.0,
      "units": "nT",
      "depth_factor": 1,
      "inclination_factor": 1,
      "azimuth_factor": 0,
      "propagation_mode": "Well",
      "depth_formula": "0",
      "inclination_formula": "0",
      "azimuth_formula": "-Sin(Inc) * Sin(AzM) * (Tan(Dip) * Cos(Inc) + Sin(Inc) * Cos(AzM)) / (1 - Sin(Inc) * Sin(Inc) * Sin(AzM) * Sin(AzM)) / Bfield",
      "north_singularity": null,
      "east_singularity": null,
      "vertical_singularity": null,
      "hash_value": "00000000000000000000000000000000"
    },
    {
      "uuid": "12633f31-68bb-5419-a0ad-6fa9ff05a219",
      "name": "MFI-OS",
      "x_owsg_weight_function": "MFI",
      "value": 88.0,
      "units": "nT",
      "depth_factor": 1,
      "inclination_factor": 1,
      "azimuth_factor": 1,
      "propagation_mode": "Global",
      "depth_formula": "0",
      "inclination_formula": "0",
      "azimuth_formula": "-Sin(Inc) * Sin(AzM) * (Tan(Dip) * Cos(Inc) + Sin(Inc) * Cos(AzM)) / (1 - Sin(Inc) * Sin(Inc) * Sin(AzM) * Sin(AzM)) / Bfield",
      "north_singularity": null,
      "east_singularity": null,
      "vertical_singularity": null,
      "hash_value": "00000000000000000000000000000000"
    },
    {
      "uuid": "ebbd6ada-c271-51d3-a993-0b524a3a75fd",
      "name": "MFI-OH",
      "x_owsg_weight_function": "MFI",
      "value": 73.0,
      "units": "nT",
      "depth_factor": 1,
      "inclination_factor": 1,
      "azimuth_factor": 1,
      "propagation_mode": "Global",
      "depth_formula": "0",
      "inclination_formula": "0",
      "azimuth_formula": "-Sin(Inc) * Sin(AzM) * (Tan(Dip) * Cos(Inc) + Sin(Inc) * Cos(AzM)) / (1 - Sin(Inc) * Sin(Inc) * Sin(AzM) * Sin(AzM)) / Bfield",
      "north_singularity": null,
      "east_singularity": null,
      "vertical_singularity": null,
      "hash_value": "00000000000000000000000000000000"
    },
    {
      "uuid": "5b41d932-d0fb-5b30-8c2c-c3a7c3953a02",
      "name": "MFI-OI",
      "x_owsg_weight_function": "MFI",
      "value": 13.0,
      "units": "nT",
      "depth_factor": 1,
      "inclination_factor": 1,
      "azimuth_factor": 1,
      "propagation_mode": "Global",
      "depth_formula": "0",
      "inclination_formula": "0",
      "azimuth_formula": "-Sin(Inc) * Sin(AzM) * (Tan(Dip) * Cos(Inc) + Sin(Inc) * Cos(AzM)) / (1 - Sin(Inc) * Sin(Inc) * Sin(AzM) * Sin(AzM)) / Bfield",
      "north_singularity": null,
      "east_singularity": null,
      "vertical_singularity": null,
      "hash_value": "00000000000000000000000000000000"
    },
    {
      "uuid": "36c4f056-8ba4-503a-aafe-015f449ba2b3",
      "name": "MFIR",
      "x_owsg_weight_function": "MFI",
      "value": 60.0,
      "units": "nT",
      "depth_factor": 0,
      "inclination_factor": 0,
      "azimuth_factor": 0,
      "propagation_mode": "Random",
      "depth_formula": "0",
      "inclination_formula": "0",
      "azimuth_formula": "-Sin(Inc) * Sin(AzM) * (Tan(Dip) * Cos(Inc) + Sin(Inc) * Cos(AzM)) / (1 - Sin(Inc) * Sin(Inc) * Sin(AzM) * Sin(AzM)) / Bfield",
      "north_singularity": null,
      "east_singularity": null,
      "vertical_singularity": null,
      "hash_value": "00000000000000000000000000000000"
    },
    {
      "uuid": "3a60b80d-1aa0-5ff3-8812-11bc0363c7b0",
      "name": "SAGE",
      "x_owsg_weight_function": "SAGE",
      "value": 0.2,
      "units": "deg",
      "depth_factor": 1,
      "inclination_factor": 0,
      "azimuth_factor": 0,
      "propagation_mode": "Systematic",
      "depth_formula": "0",
      "inclination_formula": "(Sin(Inc))^0.25",
      "azimuth_formula": "0",
      "north_singularity": null,
      "east_singularity": null,
      "vertical_singularity": null,
      "hash_value": "00000000000000000000000000000000"
    },
    {
      "uuid": "5d71dee2-d0c0-5569-a474-e6ea4967a67f",
      "name": "XYM1",
      "x_owsg_weight_function": "XYM1",
      "value": 0.1,
      "units": "deg",
      "depth_factor": 1,
      "inclination_factor": 0,
      "azimuth_factor": 0,
      "propagation_mode": "Systematic",
      "depth_formula": "0",
      "inclination_formula": "Abs(Sin(Inc))",
      "azimuth_formula": "0",
      "north_singularity": null,
      "east_singularity": null,
      "vertical_singularity": null,
      "hash_value": "00000000000000000000000000000000"
    },
    {
      "uuid": "f73b303e-df63-5f75-a1ec-e0c4770d3889",
      "name": "XYM2",
      "x_owsg_weight_function": "XYM2",
      "value": 0.1,
      "units": "deg",
      "depth_factor": 1,
      "inclination_factor": 0,
      "azimuth_factor": 0,
      "propagation_mode": "Systematic",
      "depth_formula": "0",
      "inclination_formula": "0",
      "azimuth_formula": "-1",
      "north_singularity": null,
      "east_singularity": null,
      "vertical_singularity": null,
      "hash_value": "00000000000000000000000000000000"
    },
    {
      "uuid": "349db1f2-84b8-5b7e-8d2a-47f706ebc4b5",
      "name": "XYM3E",
      "x_owsg_weight_function": "XYM3E",
      "value": 0.3,
      "units": "deg",
      "depth_factor": 0,
      "inclination_factor": 0,
      "azimuth_factor": 0,
      "propagation_mode": "Random",
      "depth_formula": "0",
      "inclination_formula": "Cos(Inc) * Cos(AzT)  * Max(1, sqrt(10/(MD-MDPrev)))",
      "azimuth_formula": "(Cos(Inc) * Sin(AzT)  / Sin(Inc)) * Max(1, sqrt(10/(MD-MDPrev)))",
      "north_singularity": "Max(1, sqrt(10/(MD-MDPrev)))",
      "east_singularity": null,
      "vertical_singularity": null,
      "hash_value": "00000000000000000000000000000000"
    },
    {
      "uuid": "29df99e7-1a2b-54c5-b387-d25011a539dc",
      "name": "XYM4E",
      "x_owsg_weight_function": "XYM4E",
      "value": 0.3,
      "units": "deg",
      "depth_factor": 0,
      "inclination_factor": 0,
      "azimuth_factor": 0,
      "propagation_mode": "Random",
      "depth_formula": "0",
      "inclination_formula": "Cos(Inc) * Sin(AzT) * Max(1, sqrt(10/(MD-MDPrev)))",
      "azimuth_formula": "(Cos(Inc) * Cos(AzT)  / Sin(Inc)) * Max(1, sqrt(10/(MD-MDPrev)))",
      "north_singularity": null,
      "east_singularity": "Max(1, sqrt(10/(MD-MDPrev)))",
      "vertical_singularity": null,
      "hash_value": "00000000000000000000000000000000"
    },
    {
      "uuid": "c72c3300-c2c8-566d-ba93-e4fecd61b001",
      "name": "XCLA",
      "x_owsg_weight_function": "XCLA",
      "value": 0.167,
      "units": "-",
      "depth_factor": 0,
      "inclination_factor": 0,
      "azimuth_factor": 0,
      "propagation_mode": "Random",
      "depth_formula": "0",
      "inclination_formula": "0",
      "azimuth_formula": "Max(Sin(Abs(AzT-AzPrev)), XCLTortuosity * (MD-MDPrev) / Sin(Inc))",
      "north_singularity": "XCLTortuosity * RAD * (MD - MDPrev)",
      "east_singularity": "XCLTortuosity * RAD * (MD - MDPrev)",
      "vertical_singularity": null,
      "hash_value": "00000000000000000000000000000000"
    },
    {
      "uuid": "380a209f-b863-596c-9434-2a2469da542c",
      "name": "XCLH",
      "x_owsg_weight_function": "XCLH",
      "value": 0.167,
      "units": "-",
      "depth_factor": 0,
      "inclination_factor": 0,
      "azimuth_factor": 0,
      "propagation_mode": "Random",
      "depth_formula": "0",
      "inclination_formula": "Max(Abs(Inc-IncPrev), XCLTortuosity* (MD-MDPrev))",
      "azimuth_formula": "0",
      "north_singularity": null,
      "east_singularity": null,
      "vertical_singularity": null,
      "hash_value": "00000000000000000000000000000000"
    }
  ],
  "hash_function": "SHA256",
  "hash_value": "00000000000000000000000000000000"
}